Metadata-Version: 1.0
Name: dsnd-probability-20191009-1
Version: 0.2
Summary: Gaussian and Binominal distributions
Home-page: UNKNOWN
Author: Takeshi Ogawa
Author-email: UNKNOWN
License: UNKNOWN
Platform: UNKNOWN
